risclog.batou-3.7.0-py3.9-nspkg.pth
risclog/batou/__init__.py
risclog/batou/appenv.py
risclog/batou/bashenv.py
risclog/batou/conftest.py
risclog/batou/disablenscd.py
risclog/batou/docker.py
risclog/batou/docserver.py
risclog/batou/filebeat.py
risclog/batou/github.py
risclog/batou/keycloak.py
risclog/batou/proftpd.py
risclog/batou/redis.py
risclog/batou/restart.py
risclog/batou/source.py
risclog/batou/userenv.py
risclog/batou/resources/alembic.ini
risclog/batou/resources/disablenscd.nix
risclog/batou/resources/filebeat.nix
risclog/batou/resources/gita
risclog/batou/resources/publish.sh
risclog/batou/resources/service.yml
risclog/batou/resources/docserver/fonts.nix
risclog/batou/resources/docserver/portal.ini
risclog/batou/resources/docserver/requirements.lock
risclog/batou/resources/keycloak/keycloak-last-login-event-listener.jar
risclog/batou/resources/keycloak/keycloak.conf
risclog/batou/resources/keycloak/keycloak.sh
risclog/batou/resources/proftpd/create_sftp_user
risclog/batou/resources/proftpd/delete_sftp_user
risclog/batou/resources/proftpd/proftpd.conf
risclog/batou/resources/proftpd/proftpd.firewall
risclog/batou/resources/proftpd/proftpd.patch
risclog/batou/resources/proftpd/proftpd.service
risclog/batou/tests/__init__.py
risclog/batou/tests/test_appenv.py
risclog/batou/tests/test_bashenv.py
risclog/batou/tests/test_disablenscd.py
risclog/batou/tests/test_docserver.py
risclog/batou/tests/test_filebeat.py
risclog/batou/tests/test_github.py
risclog/batou/tests/test_proftpd.py
risclog/batou/tests/test_redis.py
risclog/batou/tests/test_source.py
risclog.batou-3.7.0.dist-info/AUTHORS.rst
risclog.batou-3.7.0.dist-info/METADATA
risclog.batou-3.7.0.dist-info/WHEEL
risclog.batou-3.7.0.dist-info/namespace_packages.txt
risclog.batou-3.7.0.dist-info/top_level.txt
risclog.batou-3.7.0.dist-info/RECORD
