Metadata-Version: 2.1
Name: risclog.batou
Version: 3.7.0
Summary: batou extensions used by risclog
Home-page: https://github.com/risclog-solution/risclog.batou
Author: riscLOG Solution GmbH
Author-email: info@risclog.de
Keywords: risclog.batou
Classifier: Development Status :: 2 - Pre-Alpha
Classifier: Intended Audience :: Developers
Classifier: Natural Language :: German
Classifier: Programming Language :: Python :: 3
Classifier: Programming Language :: Python :: 3.9
Classifier: Programming Language :: Python :: 3.10
Requires-Python: >=3.6
License-File: AUTHORS.rst
Requires-Dist: requirements-parser <0.3
Requires-Dist: six
Requires-Dist: batou >=2.3b5
Requires-Dist: batou-ext >=2.4.27
Provides-Extra: docs
Requires-Dist: Sphinx ; extra == 'docs'
Provides-Extra: test
Requires-Dist: pytest-cache ; extra == 'test'
Requires-Dist: pytest-cov ; extra == 'test'
Requires-Dist: pytest-flake8 ; extra == 'test'
Requires-Dist: pytest-rerunfailures ; extra == 'test'
Requires-Dist: pytest-sugar ; extra == 'test'
Requires-Dist: pytest ; extra == 'test'
Requires-Dist: coverage ; extra == 'test'
Requires-Dist: flake8 <4 ; extra == 'test'
Requires-Dist: mock ; extra == 'test'
